absolutlyuseless/__init__.py
absolutlyuseless/main.py
absolutlyuseless-1.2.dist-info/LICENSE
absolutlyuseless-1.2.dist-info/METADATA
absolutlyuseless-1.2.dist-info/WHEEL
absolutlyuseless-1.2.dist-info/top_level.txt
absolutlyuseless-1.2.dist-info/RECORD
