Metadata-Version: 2.1
Name: absolutlyuseless
Version: 1.2
Summary: An absolutly useless package which you for some reason tried to download
Home-page: https://srv.dhruvsingh.com/python-proj/absolutlyuseless
Author: Thinker Designs
Author-email: dhruv@jaysingh.com
License: UNKNOWN
Platform: UNKNOWN
Classifier: Programming Language :: Python :: 3
Classifier: License :: OSI Approved :: MIT License
Classifier: Operating System :: OS Independent
Requires-Python: >=3.6
License-File: LICENSE
